missing_data_navkiran.py
missing_data_navkiran_cli.py
missing_data_navkiran-1.0.4.dist-info/LICENSE
missing_data_navkiran-1.0.4.dist-info/METADATA
missing_data_navkiran-1.0.4.dist-info/WHEEL
missing_data_navkiran-1.0.4.dist-info/entry_points.txt
missing_data_navkiran-1.0.4.dist-info/top_level.txt
missing_data_navkiran-1.0.4.dist-info/RECORD
