Metadata-Version: 2.1
Name: missing-data-navkiran
Version: 1.0.4
Summary: Handle Missing Data By Either Dropping Rows/Columns, Forward/Backward Filling or Imputing with Mean, Median or Mode
Home-page: https://github.com/navkiran/Missing_data_navkiran.git
Author: Navkiran Singh
Author-email: nsingh2_be17@thapar.edu
License: UNKNOWN
Keywords: command-line,Missing-Data
Platform: UNKNOWN
Classifier: Programming Language :: Python :: 3
Classifier: License :: OSI Approved :: MIT License
Classifier: Operating System :: OS Independent
Requires-Python: >=3.6
Requires-Dist: numpy
Requires-Dist: pandas
